expr_calc/__init__.py
expr_calc/__main__.py
expr_calc/calc.py
expr_calc/errors.py
expr_calc/operators.py
expr_calc/token.py
expr_calc/tree.py
expr_calc-0.1.2.dist-info/LICENSE
expr_calc-0.1.2.dist-info/WHEEL
expr_calc-0.1.2.dist-info/METADATA
expr_calc-0.1.2.dist-info/RECORD
