Metadata-Version: 2.1
Name: expr-calc
Version: 0.1.2
Summary: Expression interpreter modeled after a calculator
Home-page: https://github.com/lestherll/expr_calc
License: MIT
Keywords: calculator,interpreter,REPL
Author: lestherll
Author-email: ljllacuna5@gmail.com
Requires-Python: >=3.7,<4.0
Classifier: License :: OSI Approved :: MIT License
Classifier: Programming Language :: Python :: 3
Classifier: Programming Language :: Python :: 3.7
Classifier: Programming Language :: Python :: 3.8
Classifier: Programming Language :: Python :: 3.9
Project-URL: Repository, https://github.com/lestherll/expr_calc
